{
  "AndroidBoard": "Seleziona una scheda Android e inserisci la versione del programma",
  "CameraNumber": "Numero della fotocamera",
  "CameraPosition": "Posizione della fotocamera",
  "LoadingLogs": "Caricamento dei registri ...",
  "LogDetails": "Dettagli del registro",
  "ProductClass": "Colonna di classificazione dei prodotti",
  "Updatelog": "Registro aggiornamento",
  "Updatevideo": "Aggiorna la lista dei video",
  "VideoLength": "Lunghezza",
  "actCancel": "Attivazione annullare",
  "actSuccess": "Attivazione riuscita",
  "activeOneKey": "Attivazione con un clic",
  "activeTime": "Tempo di attivazione",
  "addQuick": "Crea velocemente",
  "additional": "Seleziona caratteristiche aggiuntive",
  "address": "Indirizzo del dispositivo",
  "adultAge": "età adulta",
  "adv": "Materiale pubblicitario",
  "advAdd": "Pubblicità push",
  "advCount": "Il gioco conta",
  "advCountPlaceholder": "Inserisci il numero di riproduzioni",
  "advDuration": "Tempo di gioco",
  "advExpire": "Periodo di validità",
  "advFullScreen": "annuncio a schermo intero",
  "advFullScreenCount": "Conto alla rovescia degli annunci a schermo intero",
  "advFullScreenCountPlaceholder": "Inserisci un conto alla rovescia per gli annunci a schermo intero",
  "advHalfScreen": "annuncio a metà schermo",
  "advHalfScreenHeight": "Altezza metà schermo",
  "advHalfScreenLimit": "L'altezza degli annunci a metà schermo non può superare {value}",
  "advHalfScreenMsg": "L'altezza dell'annuncio a metà schermo non può superare il 100%",
  "advPlaceholder": "Selezionare il materiale pubblicitario",
  "advPosBoth": "Lato acquisto mobile + schermo macchina",
  "advPosMachine": "Solo schermo macchina",
  "advPosMobile": "Mobile",
  "advPosMobileErr": "Il video non può essere posizionato su dispositivo mobile",
  "advPosPlaceholder": "Seleziona una posizione della schermata di posizionamento",
  "advPosition": "Posizione",
  "advPreview": "Anteprima materiale",
  "advScreenMain": "Schermo di casa",
  "advScreenPosition": "posizione dello schermo",
  "advScreenSub": "Schermo secondario",
  "advShare": "annunci di condivisione del dispositivo",
  "after_buy": "Errore di acquisto",
  "age": "età",
  "agentLog": "Record di assegnazione dell'agente",
  "agreement": "Protocollo",
  "agreementBluetooth": "Protocollo Bluetooth Rongda World",
  "agreementDKM3": "3.0 Accordo Dakoma",
  "all": "Tutte le attrezzature",
  "androidConfig": "Configurazione Android",
  "androidVersion": "versione Android",
  "androidVersionLocal": "Android nativo",
  "androidVersionPrimary": "Android normale",
  "appManager": "Gestione del programma APP",
  "appSizeMax": "Numero massimo di caricamenti raggiunto",
  "appUpdate": "aggiornamento dell'app",
  "authBluetoothManual": "Bottone blu",
  "authFacePhone": "Riconoscimento del volto + verifica mobile",
  "authIDcardPhone": "Carta d'identità + verifica del telefono cellulare",
  "authOcr": "OCR",
  "authPhone": "Solo verifica tramite cellulare",
  "authRflib": "RFLIB OCR",
  "authSwitch": "Verificare l'interruttore",
  "authentication": "Seleziona autenticazione",
  "autoVoice": "Voce induttiva",
  "axisnotrack": "Sollevamento ad asse singolo - senza binario di carico della pressa",
  "axisspring": "Sollevamento ad asse singolo - binario di carico a molla",
  "axistrack": "Sollevamento ad asse singolo - con pista di carico della pressa",
  "base": "Informazioni di base",
  "bin": "Stazione di riciclaggio",
  "bind": "Associa il dispositivo",
  "bindError": "Dispositivo non vincolato, vieta l'impostazione del costo del servizio",
  "bindTime": "Assegna tempo",
  "bluetooth": "Bluetooth",
  "bugVoice": "Acquista la voce",
  "businessMode": "Modello operativo",
  "buyAnimation": "Animazione",
  "buyLimit": "Limite di acquisto",
  "buyScan": "Scansiona e paga per un singolo prodotto",
  "buyTimes": "Tempi di acquisto",
  "buyType": "Modalità di acquisto",
  "buyTypeLable": {
    "channel": "Per scaffale (carrello)",
    "default": "Predefinito（Tutto）",
    "free": "Gratuito",
    "price": "Per prezzo（carrello）",
    "single": "Separare",
    "times": "Contare"
  },
  "camera": {
    "Addcamera": "Aggiungi fotocamera",
    "Allday": "sparatori tutto il giorno",
    "Automatic": "Segnalazione automatica",
    "BackendTrigger": "Trigger del backend",
    "Camera": "Fotocamera",
    "Camerastatus": "Stato della fotocamera",
    "Editcamera": "Modifica fotocamera",
    "Modes": "Modalità fotocamera",
    "Order": "Ordina sparatoria",
    "Ordervideo": "Ordina video",
    "Realtime": "Streaming video in tempo reale",
    "cameraMode": "modalità fotocamera",
    "enterNumber": "Inserisci il numero della fotocamera",
    "enterPath": "Inserisci il percorso di archiviazione del video",
    "management": "Gestione della fotocamera",
    "mode": "Ordina modalità di caricamento video",
    "number": "Numero della fotocamera",
    "path": "Percorso di archiviazione video",
    "switch": "Interruttore fotocamera"
  },
  "cardAdd": "Aggiungi una carte IoT",
  "cardCodePlaceholder": "Il numero della carta IoT non può essere vuoto",
  "cardTax": "Aliquota dell'imposta sul pagamento con carta di credito",
  "cartLimit": "Limite del carrello",
  "cartQuantity": "Quantità del carrello per volta",
  "channelAdd": "Aggiungi corsia di carico",
  "channelAddMore": "Aggiungi più corsie di carico",
  "channelAddSuccess": "Impossibile aggiungere le informazioni sulla corsia di carico",
  "channelBan": "Disabilitato",
  "channelBuyLimit": "Limite di acquisto su corsia unica",
  "channelCapacity": "Capacità della corsia di carico",
  "channelCapacityOver": "Non può essere maggiore della capacità della corsia di carico",
  "channelCapacityPlaceholder": "Inserisci la capacità della corsia di carico",
  "channelCodeEnd": "numero finale",
  "channelCodeEndPlaceholder": "Inserisci il numero della corsia finale",
  "channelCodeStart": "Numero iniziale",
  "channelCodeStartPlaceholder": "Inserisci il numero della traccia iniziale",
  "channelDel": "eliminare",
  "channelDelModal": "Questa operazione eliminerà definitivamente il canale, vuoi continuare?",
  "channelEdit": "Modifica",
  "channelEditSuccess": "Modifica delle informazioni sulla corsia di carico riuscita",
  "channelFloor": "Numero di strato della corsia di carico",
  "channelHot": "Vendita calda di corsia di carico",
  "channelManager": "Gestione della corsia di carico",
  "channelMap": "Mappatura delle corsie di carico",
  "channelMapPlaceholder": "Inserisci la mappatura della corsia di carico",
  "channelMistakeTimes": "Numero di errori consentiti",
  "channelMistakeTimesPlaceholder": "Inserisci il numero di errori consentiti",
  "channelOpen": "abilitare",
  "channelPrice": "Prezzi di corsia di carico",
  "channelPricePlaceholder": "Inserisci un prezzo",
  "channelProduct": "Prodotto di corsia di carico",
  "channelProductPlaceholder": "Seleziona un prodotto di corsia di carico",
  "channelRetry": "Ripetizione della spedizione dopo una spedizione non andata a buon fine",
  "channelStock": "Inventario della corsia di carico",
  "channelStockErr": "Non può essere inferiore all'inventario della corsia di carico",
  "channelStockPlaceholder": "Inserisci l'inventario della corsia di carico",
  "channelType": "Tipo di corsia di carico",
  "channelType2": "Sottotipo di corsia di trasporto",
  "channelTypePlaceholder": "Seleziona un tipo di corsia di carico",
  "channelWarning": "Avviso corsia di carico",
  "clone": "clone",
  "codeFormt": "Il numero del dispositivo deve essere di 4 lettere o numeri",
  "codeMin": "Il numero del dispositivo non può essere inferiore a 6 cifre",
  "codePrefix": "Prefisso del codice",
  "codePrefixMsg": "Inserisci da 3 a 4 cifre",
  "codePrefixPlaceholder": "Inserisci un prefisso numerico",
  "codeStart": "Inizio del codice",
  "codeStartPlaceholder": "Si prega di inserire un numero di partenza",
  "coin": {
    "add": "Aggiungi magazzino valuta",
    "capacity": "Capacità",
    "code": "Magazzino n.",
    "currencyCode": "Codice valuta",
    "currencyName": "nome della valuta",
    "currencySymbol": "Simbolo di valuta",
    "currencyValue": "Valore della valuta",
    "hardMoney": "Moneta",
    "log": "Registro del magazzino delle monete",
    "logClear": "Svuota il magazzino valuta",
    "logSubmit": "Segnala le scorte di valuta",
    "logType": "tipo di registro",
    "manager": "Gestione Magazzino Valute",
    "paperMoney": "Banconote",
    "refund": "magazzino di rimborso",
    "stockCurrent": "Inventario attuale",
    "type": "Tipo di valuta",
    "warehouseSave": "Magazzino di risparmio",
    "warehouseType": "Tipo di magazzino"
  },
  "combineProduct": "Combina gli stessi prodotti",
  "communication": "Seleziona comunicazione",
  "completeCargo": "Si prega di compilare le informazioni complete sul canale merci",
  "compr": "compressore",
  "config": "Configurazione del dispositivo",
  "controlBoard": "Selezionare la scheda di controllo industriale e inserire la versione del programma",
  "coord": "coordinate del dispositivo",
  "copyChannel": "Copia corsia",
  "copyTarget": "Copia sul dispositivo di destinazione",
  "currency": "valuta di transazione",
  "delBatch": "eliminazione batch",
  "detail": "Informazioni dettagliate",
  "displayBalance": "Interruttore del saldo (moneta + carta di scorrimento)",
  "displayInventory": "Mostra l'interruttore dell'inventario",
  "domain": "Dominio",
  "domainPlaceholder": "Immettere il nome di dominio dell'interfaccia",
  "durationPlaceholder": "Seleziona un periodo di tempo",
  "edit": "Modifica le informazioni sul dispositivo",
  "editBatch": "Modifica batch",
  "editSuccess": "Modifica le informazioni sul dispositivo con successo",
  "editSuccessSome": "Alcune informazioni sono state aggiunte correttamente",
  "eidtTips": "Non inserire se non si desidera modificare il contenuto",
  "expire": "Durata di conservazione",
  "expirePlaceholder": "Seleziona una data di scadenza",
  "external": "esterno",
  "fileName": "nome file",
  "flow": "fluire",
  "flowDeadlineText": "Data di scadenza",
  "flowPackAll": "Il flusso totale del pacchetto",
  "flowRemain": "flusso residuo",
  "flowRemainText": "flusso residuo",
  "flowUsed": "flusso utilizzato",
  "formEmptyAlert": "I valori nulli non verranno modificati",
  "free": "Ottienilo gratis",
  "freeAfter": "Disponibile per l'acquisto dopo il ritiro gratuito",
  "freePlaceholder": "Di default 0, 1 diviso per il valore corrente per calcolare l'intervallo in giorni",
  "fullScreenSwitch": "Schermo intero o no",
  "handleBatch": "Operazioni batch",
  "handleResult": "Risultato dell'operazione",
  "handleTime": "Tempo di funzionamento",
  "handleType": "Tipo di operazione",
  "handler": "operatore",
  "help": "Aiuto dispositivo",
  "host": "indirizzo IP del server",
  "hostPlaceholder": "Si prega di inserire l'indirizzo IP del server",
  "hostPort": "porta",
  "img": "Immagini dell'attrezzatura",
  "info": "Informazioni sul dispositivo",
  "internal": "interno",
  "listTimeout": "Recuperare il timeout dell'elenco dei file video",
  "lock": "Serratura",
  "lockClose": "Vicino",
  "lockCode": "Serratura",
  "lockLog": "Registro serratura elettronica",
  "lockOpen": "Aprire",
  "machineAdd": "Aggiungi dispositivo",
  "machineAddBatch": "Aggiungi dispositivi in ​​blocco",
  "machineBin": "Stazione di riciclaggio delle attrezzature",
  "machineClone": "dispositivo di clonazione",
  "machineCode": "Codice QR del dispositivo",
  "machineEmpty": "Ancora nessuna informazione sul dispositivo!",
  "machineHandleSelect": "Seleziona un dispositivo da utilizzare",
  "machineLock": "Serratura",
  "machineLockSub": "Secondo",
  "machineManager": "Gestione dei dispositivi",
  "machineRegStatus": "Stato di registrazione del dispositivo",
  "maxTwoMsg": "Il valore massimo può essere solo di due cifre",
  "modalActServe": "Questa azione attiverà il periodo di servizio del dispositivo, vuoi continuare?",
  "modalDel": "Questa azione eliminerà definitivamente il dispositivo, continuare?",
  "mode": "modalità dispositivo",
  "modePlaceholder": "Seleziona una modalità del dispositivo",
  "motor": "Classe motoria",
  "msgActMachineNone": "Nessun dispositivo rilevato che richiede l'attivazione",
  "number": "aggiungi quantità",
  "numberLimit": "Limite di acquisto",
  "numberLimitPlaceholder": "Inserisci il limite di acquisto (0 significa nessun limite di acquisto, il valore predefinito è 0)",
  "numberPlaceholder": "Inserisci il numero di dispositivi",
  "offlineTime": "tempo offline",
  "onlineDetail": "Dettagli in linea dell'attrezzatura",
  "onlineDuration": "Tempo in linea",
  "onlineDurationMsg": "(basato sull'ora di Pechino)",
  "onlineLongPlan": "Tempo online stimato",
  "onlinePlan": "Programma in linea",
  "onlineStatus": "In linea",
  "onlineTime": "tempo in linea",
  "onlineTimePlan": "Tempo online stimato",
  "onlineYesterday": "Orario online ieri",
  "operator": "operatore",
  "organization": "Organizzazione",
  "outChannelDiffer": "Stessa merce su corsie diverse",
  "outErrorRefund": "Rimborso in caso di errore",
  "outFailedRetry": "Rispedire in caso di errore",
  "outOverRefund": "Rimborso allo scadere del tempo",
  "overduePay": "Pagare gli arretrati",
  "overduePayment": "Pagare gli arretrati",
  "password": "parola d'ordine",
  "payCancel": "annullare il pagamento",
  "payConfirm": "confermare il pagamento",
  "payModule": "Modulo di pagamento",
  "payTimesPlaceholder": "Inserisci il numero corretto di acquisti",
  "payTypePlaceholder": "Si prega di selezionare il metodo di pagamento",
  "payVoice": "Voce di pagamento",
  "payYears": "Periodo di pagamento",
  "payYearsPlaceholder": "Si prega di selezionare il periodo di pagamento",
  "playTimePlaceholder": "Si prega di inserire il tempo di riproduzione",
  "port": "prot",
  "portPlaceholder": "Immettere il numero di porta del server",
  "position": "Posizione",
  "price": "prezzo unitario",
  "priceAll": "prezzo totale",
  "productChange": "merce",
  "productCol": "colonne",
  "productColMsg": "Il numero di colonne prodotto non può superare 10",
  "productColPlaceholder": "Inserisci il numero di colonne del prodotto (1-10)",
  "productHeight": "Altezza del prodotto",
  "productHeightLimit": "L'altezza del prodotto non può superare {valore}",
  "productHeightMsg": "L'altezza del prodotto non può superare i 125px",
  "productHeightPlaceholder": "Si prega di inserire l'altezza del prodotto",
  "productRollDirction": "Direzione di scorrimento",
  "productRollX": "scorri a sinistra e a destra",
  "productRollY": "scorrere su e giù",
  "productRow": "Righe",
  "productRowMsg": "Numero di righe di prodotti non può superare le 10 righe",
  "productRowPlaceholder": "Inserisci il numero di righe di prodotti (1-10)",
  "productScreenShow": "Merce per lo schermo",
  "purchaseMOQ": "Acquisto singolo canale",
  "pushMotor": "Motore a spinta",
  "qrcodeExport": "Esporta codice QR",
  "qrcodeFullScreen": "Codice QR pubblicitario a schermo intero",
  "qrcodeLoadSuccess": "Generato con successo",
  "qrcodeReload": "rigenerare",
  "quantityMin": "Quantità minima di acquisto",
  "recordingTime": "Tempo di registrazione",
  "recovery": "Recupero",
  "recoveryFailed": "Recupero non riuscito",
  "recoverySuccess": "recupero riuscito",
  "regStatusHad": "registrato",
  "regStatusNever": "non registrato",
  "regSuccess": "Registrazione riuscita",
  "remove": "mettere nel stazione di riciclaggio",
  "renew": "Rinnovo",
  "renewPrice": "Prezzo unitario di rinnovo",
  "renewPriceAll": "Prezzo totale di rinnovo",
  "renewSuccess": "Rinnovo riuscito",
  "renewTime": "Tempo di rinnovo",
  "renewTimeSelect": "Selezionare l'anno",
  "renewType": "Tipo di rinnovo",
  "renewYears": "Periodo di rinnovo",
  "renewYearsAll": "durata totale del rinnovo",
  "renewer": "Utenti rinnovati",
  "repFailed": "Rifornimento fallito",
  "repOneKey": "Rifornimento con un solo clic",
  "repSuccess": "Rifornimento riuscito",
  "repeat": "ripetere",
  "repeatPlaceholder": "Seleziona un tempo di ripetizione",
  "role": "informazioni sul ruolo",
  "roleBind": "Ruoli vincolanti",
  "roleHandler": "Identità dell'operatore",
  "runTime": "tempo di esecuzione",
  "screenCount": "conto alla rovescia dello schermo",
  "screenCountPlaceholder": "Inserisci un conto alla rovescia",
  "screenSize": "Seleziona la dimensione dello schermo",
  "sensor": "sensore",
  "serveDeadline": "Data di scadenza",
  "serveFee": "costo del servizio",
  "serveFeeOnekey": "Rinnovo con un clic",
  "serveFeePlatform": "Costo del servizio della piattaforma",
  "serveFeeRenew": "Rinnovo canone di servizio",
  "serveFeeSet": "Impostazioni dei costi di servizio",
  "serveFeeYear": "Tassa annuale",
  "serveFeeYearPlaceholder": "Si prega di inserire il canone annuale di servizio dell'attrezzatura",
  "serveLimit": "Durata del servizio",
  "servePhone": "Contatto",
  "set": "Impostazioni del dispositivo",
  "setValPlaceholder": "Si prega di inserire il valore di impostazione",
  "settingAdvance": "impostazioni avanzate",
  "signal": "Segnale",
  "signalCheck": "Si consiglia di controllare le condizioni del segnale della scena dell'apparecchiatura",
  "signalNone": "Il dispositivo non ha segnale",
  "signalOffline": "Il dispositivo è offline",
  "signalStrong": "Il dispositivo ha un buon segnale",
  "signalWeak": "Il segnale del dispositivo è debole",
  "sim": "Carta IoT",
  "simActTimeText": "Tempo di attivazione",
  "simAdd": "aggiungi scheda sim",
  "simCard": "carta SIM",
  "simCharge": "Rinnovo della carta IoT",
  "simCode": "Numero della carta IoT",
  "simCodePlaceholder": "Inserisci il numero della carta IoT",
  "simDel": "rimuovere la scheda SIM",
  "simFeeYear": "sim quota annuale",
  "simFeeYearPlaceholder": "Si prega di inserire la tariffa annuale della carta SIM",
  "simLimit": "data di scadenza della scheda SIM",
  "simPackType": "tipo di pacchetto",
  "simPlaceholder": "Seleziona una carta IoT",
  "simQuantitative": "Scheda IoT quantitativa",
  "simRenew": "rinnovo della sim card",
  "simSetting": "impostazioni della tariffa della carta SIM",
  "simStatus": "Stato della carta IoT",
  "simStatusAct": "Usando",
  "simStatusBan": "Già disabilitato",
  "simStatusInact": "Non attivato",
  "simStatusPlaceholder": "Seleziona lo stato della carta",
  "simStatusStop": "Non più in uso",
  "simType": "tipo di carta",
  "simTypePlaceholder": "Seleziona il tipo di carta",
  "simTypeSamton": "Scheda IoT punto medio",
  "site": "Scena dell'attrezzatura",
  "siteAdd": "Aggiungi una scena",
  "siteEdit": "Modifica la scena",
  "some": "Parte dell'attrezzatura",
  "spring": "Primavera",
  "stats": {
    "fault": "Numero di dispositivi difettosi",
    "offline": "Numero di dispositivi offline",
    "online": "Numero di dispositivi online",
    "stock": "Numero di dispositivi esauriti",
    "total": "Numero totale di dispositivi"
  },
  "status": "stato del dispositivo",
  "statusBan": "Già disabilitato",
  "statusErr": "Guasto",
  "statusNormal": "normale",
  "statusShort": "insufficiente",
  "statusTest": "Test in corso",
  "stockCheck": "Controllo delle scorte",
  "stockCheckTips": "Questo dispositivo è in grado di rilevare le scorte",
  "stockRate": "Percentuale di inventario",
  "stockStatus": "stato delle scorte",
  "taxRate": "Aliquota dell'imposta sui consumi",
  "taxRateOnline": "aliquota fiscale del pagamento online",
  "temp": "temperatura",
  "tempControl": "controllo della temperatura",
  "tempCurrent": "Temperatura attuale",
  "tempRange": "L'intervallo di temperatura è -25 ℃ ~ 55 ℃",
  "tempSet": "impostazione della temperatura",
  "tempSetPlaceholder": "Si prega di inserire l'impostazione della temperatura",
  "tempSetting": "Impostazioni di controllo della temperatura",
  "tempSwitch": "interruttore del compressore",
  "tempTaskAdd": "Aggiunta di attività a tempo",
  "tempTaskDel": "Se eliminare l'attività temporizzata di controllo della temperatura",
  "tempValue": "valore impostato",
  "tempWarning": "Avvertire la temperatura",
  "tempWarningPlaceholder": "Immettere la temperatura di avviso del dispositivo",
  "template": {
    "add": "Modello DDD",
    "addChannel": "Aggiungi corsia di carico",
    "additional": "funzione aggiuntiva",
    "androidBoardConfig": "Configurazione della scheda Android",
    "androidboard": "Scheda Android",
    "authentication": "Autenticazione",
    "coinWarehouse": "Deposito monete",
    "communication": "Comunicazione",
    "controlBoard": "scheda di controllo",
    "customize": "personalizza",
    "defaultLang": "lingua predefinita",
    "delTip": "Questa operazione cancellerà i dati? \nVuoi continuare?",
    "enter": "Inserisci il nome del modello",
    "enterAndroid": "Inserisci informazioni sulla scheda Android",
    "enterAndroidName": "Inserisci il nome della scheda Android",
    "enterCode": "Inserisci il numero della traccia",
    "enterControlName": "Inserire il nome della scheda di controllo",
    "enterDeviceType": "Inserisci il tipo di dispositivo",
    "enterFormat1": "Il formato di ingresso è: 5-19 pollici (gerarchia di posizione è 5, dimensione è 19 pollici)",
    "enterFormat2": "Il formato di input è: 5-free payment (5 è la gerarchia della posizione, il pagamento gratuito è il nome)",
    "enterFreightType": "Inserisci il tipo di canale di carico",
    "enterLayer": "Strato di corsia di carico di ingresso",
    "enterVerification": "Inserisci la verifica dell'identità",
    "enterVersion": "Inserisci la versione del programma (protocollo)",
    "enterVersion2": "Inserisci la versione del programma (data)",
    "equipment": "Modello di attrezzatura",
    "freightChannel": "Canale merci",
    "freightDetails": "Dettagli del canale di carico",
    "freightLayer": "Strato del corridoio merci",
    "name": "Nome del modello",
    "oneCancel": "Annullamento di un clic",
    "oneCheck": "Controllo di un clic",
    "pleaseControl": "Selezionare la scheda di controllo industriale",
    "prohibit": "Vietare",
    "screenSize": "Dimensioni dello schermo",
    "set": "Impostazioni del modello",
    "state": "stato",
    "templateDetails": "Dettagli del modello",
    "version": "Versione"
  },
  "testMode": "modalità di prova",
  "timerType": "Tipo di temporizzazione",
  "track": "Traccia",
  "type": "Tipo di apparecchiatura",
  "typeAndroid": "Dispositivo Android",
  "typeBluetooth": "dispositivo bluetooth",
  "typeDTU": "Apparecchiatura DTU",
  "typePlaceholder": "Seleziona il tipo di dispositivo",
  "unBindMsg": "Dispositivi non vincolati, nessun rinnovo",
  "unset": "non impostato",
  "updateData": "Aggiorna i dati",
  "updateSuccess": "Aggiornamento riuscito",
  "versiionSize": "Dimensione del file",
  "version": "numero della versione",
  "versionAdd": "Aggiungi il numero di versione",
  "versionDel": "Questa operazione cancellerà il file della versione dell'App, se continuare o meno",
  "versionFile": "file di versione",
  "versionFilePlaceholder": "Si prega di caricare il file della versione",
  "versionMark": "Note sulla versione",
  "versionPlaceholder": "Inserisci il numero di versione",
  "versionPush": "Quest'azione spingerà il file della versione dell'app, continuare o meno",
  "versionPushSuccess": "Spingi con successo",
  "versionSelect": "Selezione del dispositivo",
  "versionUpdate": "aggiornare il dispositivo",
  "versionUpdateTime": "tempo di aggiornamento",
  "video": {
    "code": "ID del dispositivo",
    "duration": "Durata del tempo",
    "tv": "Video dell'attrezzatura",
    "unData": "Nessun dato"
  },
  "videoFiles": "Aggiornare i file video",
  "view": "vista",
  "viewVideo": "visualizzare il video",
  "voice": "voce",
  "warning": "allerta precoce",
  "xaxis": "Asse X",
  "xyaxis": "Asse XY",
  "yaxis": "Asse Y"
}
