{
  "DistributeTypes": "Verteilung",
  "able": "Bereits geöffnet",
  "actTime": "Aktivierungszeit",
  "advEarning": "Geteilte Werbeeinnahmen",
  "advEarningPlaceholder": "Bitte geben Sie die geteilten Werbeeinnahmen ein",
  "advancedSetting": "Erweiterte Einstellungen",
  "agentAccount": "Agentenkonto",
  "agentAccountPlaceholder": "Bitte geben Sie das Agentenkonto ein",
  "agentAdd": "Erstellen Sie einen Agenten",
  "agentDelMsg": "Durch diesen Vorgang werden die Rolle und das Konto dauerhaft gelöscht und der Kontostand wird gelöscht und kann nicht wiederhergestellt werden. \nMöchtest du fortfahren?",
  "agentEarnings": "Agenteneinnahmen",
  "agentIncome": "Einnahmen der Agentur",
  "agentIncomePlaceholder": "Bitte geben Sie den Maklerumsatz ein",
  "agentManager": "Agentenverwaltung",
  "agentName": "Name des Agenten",
  "agentNameEmpty": "Der Agentenname darf nicht leer sein",
  "agentNamePlaceholder": "Bitte geben Sie den Agentennamen ein",
  "agentPassword": "Agentenpasswort",
  "agentPasswordPlaceholder": "Bitte geben Sie das Agentenpasswort ein",
  "agentUp": "Überlegener Agent",
  "alipayID": "Alipay AppID",
  "alipayIDPlaceholder": "Bitte geben Sie die Alipay AppID ein",
  "alipayMerchant": "Händlerkonto (PID)",
  "alipayMerchantPlaceholder": "Bitte geben Sie das Händlerkonto (PID) ein.",
  "alipayPublic": "Öffentlicher Schlüssel des Alipay-Zertifikats",
  "alipayPublicPath": "Pfad zum öffentlichen Schlüssel des App-Zertifikats",
  "alipayPublicPathPlaceholder": "Bitte laden Sie den Pfad zum öffentlichen Schlüssel des App-Zertifikats hoch",
  "alipayPublicPlaceholder": "Bitte laden Sie den öffentlichen Alipay Cert-Schlüssel hoch",
  "alipayRoot": "Alipay-Root-Zertifikat",
  "alipayRootPlaceholder": "Bitte laden Sie das Alipay-Root-Zertifikat hoch",
  "alipaySecret": "Privater App-Schlüssel",
  "alipaySecretPlaceholder": "Bitte geben Sie den privaten App-Schlüssel ein",
  "alipaySetting": "Alipay-Zahlungseinstellung",
  "alipaySwitch": "Alipay-Schalter",
  "alipayUnset": "Alipay-Informationen sind für die Rolle nicht konfiguriert",
  "aloneEarnings": "Monopolisieren",
  "applyList": "Anwendungsliste",
  "applyTime": "Bewerbungszeitpunkt",
  "bankCardBack": "Rückseite der Bankkarte",
  "bankCardCode": "Bankkartennummer",
  "bankCardFront": "Vorderseite der Bankkarte",
  "bankOpen": "Einlagenbank",
  "base": "Grundinformation",
  "checkOpinion": "Rezensionsmeinung",
  "checkResult": "Überprüfen Sie die Ergebnisse",
  "checkStatus": "Überprüfungsstatus",
  "checkStatusPass": "Passieren",
  "checkStatusReject": "Scheitern",
  "checkStatusRejectOpinion": "Gründe für das Nichtbestehen der Prüfung",
  "checkStatusWait": "Überprüft werden",
  "checkTime": "Überprüfungszeit",
  "checker": "Rezensent",
  "clearSuccess": "Erfolgreich gelöscht",
  "copyEmailToAgent": "Möchten Sie die E-Mail-Vorlage des aktuellen Kontos auf diesen Agenten kopieren?",
  "customerAccount": "Kundenkonto",
  "customerAccountPlaceholder": "Bitte geben Sie das Kundenkonto ein",
  "customerAdd": "Kunde hinzufügen",
  "customerInfo": "Kundeninformation",
  "customerName": "Kundenname",
  "customerNamePlaceholder": "Bitte geben Sie den Namen des Kunden ein",
  "customerPassword": "Kundenpasswort",
  "customerPasswordPlaceholder": "Bitte geben Sie das Kundenpasswort ein",
  "customerStatus": "Kundenstatus",
  "defaultCurrency": "Standardwährung",
  "distributeNow": "Sofort",
  "distributeType": {
    "alipay": "T 1 Alipay verteilt Gewinn",
    "jd": "JD verteilt Gewinn",
    "title": "Gewinnverteilungsmethode",
    "wallet": "Elektronische Geldbörse",
    "wechat": "T 1 WeChat verteilt Gewinn"
  },
  "distributeTypePlaceholder": "Bitte wählen Sie die Gewinnausschüttungsmethode",
  "doorUnlockNotice": "Türentriegelung",
  "due": "Auslaufend",
  "earningRate": "Gewinnausschüttungsquote",
  "earningSetting": "Verdiensteinstellung",
  "earningStatus": "Status der Gewinnausschüttung",
  "editBelong": "Eigentümer ändern",
  "enterCallback": "Bitte geben Sie die Rückrufadresse ein",
  "enterInterface": "Bitte geben Sie die Schnittstellennummer ein",
  "expire": "Abgelaufen",
  "expireClose": "Läuft bald ab",
  "expireNotice": "Ware abgelaufen",
  "expireNumber": "Abgelaufene Menge",
  "expireTime": "Ablaufdatum",
  "fee": "Bearbeitungsgebühr",
  "feeSetting": "Einstellung der Bearbeitungsgebühr",
  "feeSettingPlaceholder": "Maßstab 1:1000",
  "idCard": "ID Kartennummer",
  "idCardBack": "Rückseite des Personalausweises",
  "idCardFront": "Vorderseite des Personalausweises",
  "jdAccount": "JD-Konto",
  "jdDesSecret": "JD desKey",
  "jdDesSecretPlaceholder": "Bitte geben Sie den JD desKey ein",
  "jdDistributeAccount": "JD-Gewinnausschüttungskonto",
  "jdDistributeType": "JD-Verteilung",
  "jdEmail": "JD-Gewinnverteilungspostfach",
  "jdMd5Secret": "JD md5Key",
  "jdMd5SecretPlaceholder": "Bitte geben Sie den JD md5Key ein",
  "jdMerchant": "JD-Händlerkonto",
  "jdMerchantEmail": "JD-Händlerpostfach",
  "jdMerchantEmailPlaceholder": "Bitte geben Sie das JD-Händlerpostfach ein",
  "jdMerchantPlaceholder": "Bitte geben Sie das JD-Händlerkonto ein",
  "jdPaySetting": "JD-Zahlungskonfiguration",
  "jdSwitch": "JD-Gewinnverteilungsschalter",
  "jdmail": "JD-Postfach",
  "level": "Grad",
  "lockNotice": "Sperrschalter",
  "machineBan": "Deaktivieren",
  "machineBin": "Papierkorb",
  "machineMistake": "Fehler",
  "machineNomal": "Normal",
  "machineNumber": "Gerätemenge",
  "machineNumberPlaceholder": "Bitte geben Sie die Geräteanzahl ein",
  "mistakeNotice": "Gerätefehler",
  "msgDel": "Durch diesen Vorgang werden die Rolle und das Konto dauerhaft gelöscht und der Kontostand wird gelöscht und kann nicht wiederhergestellt werden. \nMöchtest du fortfahren?",
  "noticeSetting": "Benachrichtigung",
  "officeAppID": "Offizielle Konto-AppID",
  "officeAppIDPlaceholder": "Bitte geben Sie die offizielle Konto-AppID ein",
  "officeID": "Die ursprüngliche ID des offiziellen Kontos",
  "officeIDPlaceholder": "Bitte geben Sie die Original-ID des offiziellen Kontos ein",
  "officeKey": "Offizielles Konto EncodingAESKey",
  "officeKeyPlaceholder": "Bitte geben Sie den offiziellen Account EncodingAESKey ein",
  "officeName": "Offizieller Kontoname",
  "officeNamePlaceholder": "Bitte geben Sie den offiziellen Kontonamen ein",
  "officeSecrect": "Offizielles Konto APPSECRECT",
  "officeSecrectPlaceholder": "Bitte geben Sie das offizielle Konto APPSECRECT ein",
  "officeSetting": "Offizielle Kontoeinstellung",
  "officeSwitch": "Offizieller Kontowechsel",
  "officeToken": "Offizielles Konto TOKEN",
  "officeTokenPlaceholder": "Bitte geben Sie das offizielle Konto-TOKEN ein",
  "officeTxt": "TXT-Datei zur Überprüfung der Sicherheit des Domänennamens",
  "officeTxtPlaceholder": "Bitte laden Sie die Sicherheitsüberprüfungsdatei für den Domainnamen hoch",
  "officeUrl": "Offizielle Konto-URL",
  "offlineNotice": "Gerät offline",
  "onlineNotice": "Gerät online",
  "owingMoney": "Betrag im Rückstand",
  "partnerAccount": "Partnerkonto",
  "partnerAccountPlaceholder": "Bitte Partnerkonto eingeben",
  "partnerAdd": "Erstellen Sie einen Partner",
  "partnerEarnings": "Partnereinkommen",
  "partnerEarningsPlaceholder": "Bitte geben Sie das Partnereinkommen ein",
  "partnerManager": "Partnermanagement",
  "partnerName": "Partnername",
  "partnerNamePlaceholder": "Bitte geben Sie den Namen des Partners ein",
  "partnerPassword": "Partnerpasswort",
  "partnerPasswordPlaceholder": "Bitte geben Sie das Partnerpasswort ein",
  "partykey": "Schlüsselkonfiguration von Drittanbietern",
  "payB2C": "Geschäftszahlung zu ändern",
  "promoApply": "Bewerbung als Promoter",
  "promoBelong": "Eigentum des Veranstalters",
  "promoCheck": "Rezension des Veranstalters",
  "promoManager": "Promotermanagement",
  "promoName": "Name des Promoters",
  "promoSelect": "Bitte wählen Sie einen Veranstalter aus",
  "promoStatus": "Promoter-Status",
  "realName": "Tatsächlicher Name",
  "receiverAccount": "Zahlungsempfängerkonto",
  "receiverName": "Name des Zahlungsempfängers",
  "repAccount": "Merchandiser-Konto",
  "repAccountPlaceholder": "Bitte geben Sie das Merchandiser-Konto ein",
  "repAdd": "Merchandiser erstellen",
  "repManager": "Merchandiser-Management",
  "repName": "Name des Merchandisers",
  "repNamePlaceholder": "Bitte geben Sie den Namen des Merchandisers ein",
  "repPassword": "Merchandiser-Passwort",
  "repPasswordPlaceholder": "Bitte geben Sie das Merchandiser-Passwort ein",
  "repairAccount": "Wartungskonto",
  "repairAccountPlaceholder": "Bitte geben Sie das Wartungskonto ein",
  "repairAdd": "Wartung hinzufügen",
  "repairManager": "Wartungsverwaltung",
  "repairPassword": "Wartungspasswort",
  "repairPasswordPlaceholder": "Bitte geben Sie das Wartungspasswort ein",
  "repairname": "Wartungsname",
  "repairnamePlaceholder": "Bitte geben Sie den Wartungsnamen ein",
  "saleNotice": "Verkauf",
  "salesDayNotice": "Tägliche Verkäufe",
  "salesMonthNotice": "Monatsumsatz",
  "salesYearNotice": "Jahresumsatz",
  "secretKey": "geheimer Schlüssel",
  "serveDeadline": "Dienstzeit",
  "serveFeeAll": "Gesamte Servicegebühr",
  "serveFeeGet": "Gebühr erhalten",
  "serveFeeState": "Servicegebühr (bezahlt/unbezahlt)",
  "serveFeeStay": "Aufgeladen werden",
  "serveFeeYear": "Jahresgebühr",
  "sim": "IoT-Karte",
  "simList": "IoT-Kartenliste",
  "simNumber": "IoT-Kartenmenge",
  "siteAccount": "Standortkonto",
  "siteAccountPlaceholder": "Bitte geben Sie das Standortkonto ein",
  "siteAdd": "Standort erstellen",
  "siteEarnings": "Verdienste",
  "siteEarningsPlaceholder": "Bitte geben Sie die Einnahmen des Veranstaltungsortes ein",
  "siteManager": "Standortverwaltung",
  "siteName": "Standortnamen",
  "siteNamePlaceholder": "Bitte geben Sie den Standortnamen ein",
  "sitePassword": "Standortpasswort",
  "sitePasswordPlaceholder": "Bitte geben Sie das Standortpasswort ein",
  "stockNotice": "Geringer Bestand",
  "stockTradeMsg": "Nachdem die Rechnungsstellung ausgewählt wurde, kann sie nicht mehr geändert werden. \nMöchtest du fortfahren?",
  "tempNotice": "Hitzealarm",
  "tokenUrl": "Rückruf-URL",
  "unable": "Nicht geöffnet",
  "warehouseGoodsNotice": "Aktie",
  "warehouseStockNotice": "Gesamtbestand",
  "weakSignalNotice": "Schwaches Signal",
  "wechatAppId": "WeChat Pay AppID",
  "wechatAppIdPlaceholder": "Bitte geben Sie die WeChat Pay AppID ein",
  "wechatCert": "CERT-Zertifikat",
  "wechatCertPlaceholder": "Bitte laden Sie das CERT-Zertifikat hoch",
  "wechatKey": "Schlüsselzertifikat",
  "wechatKeyPlaceholder": "Bitte laden Sie das Schlüsselzertifikat hoch",
  "wechatMerchant": "WeChat Pay-Händler-ID",
  "wechatMerchantPlaceholder": "Bitte geben Sie die WeChat Pay-Händler-ID ein",
  "wechatPaySetting": "WeChat-Zahlungseinstellung",
  "wechatSecrect": "WeChat-Zahlungsschlüssel",
  "wechatSecrectPlaceholder": "Bitte geben Sie den WeChat-Zahlungsschlüssel ein",
  "wechatSwitch": "WeChat-Zahlungsschalter"
}
